{
  "employees": [
    {
      "id": 1,
      "name": "Mark Zuker",
      "gender": "Male",
      "contactPreference": "Email",
      "email": "mark@pragimtech.com",
      "dateOfBirth": "1988/10/25",
      "department": "104",
      "isActive": true,
      "photoPath": "assets/images/mark.png",
      "phoneNumber": "9965982578"
    },
    {
      "id": 2,
      "name": "Mary",
      "gender": "Female",
      "contactPreference": "Phone",
      "phoneNumber": 2345978640,
      "dateOfBirth": "1979/11/20",
      "department": "105",
      "isActive": true,
      "photoPath": "assets/images/mary.png",
      "email": "marry@gmail.com"
    },
    {
      "id": 4,
      "name": "varathan",
      "gender": "Male",
      "email": "varathan@gmail.com",
      "phoneNumber": "9965982578",
      "contactPreference": "Email",
      "dateOfBirth": "2018-12-08T18:30:00.000Z",
      "department": "102",
      "isActive": true,
      "photoPath": "assets/images/mark.png"
    },
    {
      "id": 5,
      "name": "Thenz",
      "gender": "Male",
      "email": "thenz@yahoo.com",
      "phoneNumber": "5432978640",
      "contactPreference": "Email",
      "dateOfBirth": "1988-10-24T18:30:00.000Z",
      "department": "102",
      "isActive": true,
      "photoPath": "assets/images/john.png"
    }
  ]
}